Metadata-Version: 2.1
Name: simassis
Version: 0.2.1
Summary: A python Package for MD calculations in solids
Home-page: https://github.com/marcinkrynskipw/simassis
Author: Marcin Krynski
Author-email: marcin.krynski@pw.edu.pl
License: BSD 2-clause
Classifier: Development Status :: 1 - Planning
Classifier: Intended Audience :: Science/Research
Classifier: License :: OSI Approved :: BSD License
Classifier: Operating System :: POSIX :: Linux
Classifier: Programming Language :: Python :: 3
Classifier: Programming Language :: Python :: 3.4
Classifier: Programming Language :: Python :: 3.5
Requires-Dist: numpy
Requires-Dist: scipy
